certbot_dns_alicloud/__init__.py
certbot_dns_alicloud/__pycache__/__init__.cpython-314.pyc
certbot_dns_alicloud/_internal/__init__.py
certbot_dns_alicloud/_internal/dns_alicloud.py
certbot_dns_alicloud/_internal/__pycache__/__init__.cpython-314.pyc
certbot_dns_alicloud/_internal/__pycache__/dns_alicloud.cpython-314.pyc
certbot_dns_alicloud-0.0.2.dist-info/licenses/LICENSE.txt
certbot_dns_alicloud-0.0.2.dist-info/METADATA
certbot_dns_alicloud-0.0.2.dist-info/WHEEL
certbot_dns_alicloud-0.0.2.dist-info/entry_points.txt
certbot_dns_alicloud-0.0.2.dist-info/top_level.txt
certbot_dns_alicloud-0.0.2.dist-info/RECORD
