Metadata-Version: 2.4
Name: certbot-dns-alicloud
Version: 0.0.2
Summary: AliCloud DNS Authenticator plugin for Certbot
Home-page: https://github.com/certbot/certbot
Author: Jules
Author-email: certbot-dev@eff.org
License: Apache License 2.0
Classifier: Development Status :: 5 - Production/Stable
Classifier: Environment :: Plugins
Classifier: Intended Audience :: System Administrators
Classifier: License :: OSI Approved :: Apache Software License
Classifier: Operating System :: POSIX :: Linux
Classifier: Programming Language :: Python
Classifier: Programming Language :: Python :: 3
Classifier: Programming Language :: Python :: 3.6
Classifier: Programming Language :: Python :: 3.7
Classifier: Programming Language :: Python :: 3.8
Classifier: Programming Language :: Python :: 3.9
Classifier: Programming Language :: Python :: 3.10
Classifier: Topic :: Internet :: WWW/HTTP
Classifier: Topic :: Security
Classifier: Topic :: System :: Installation/Setup
Classifier: Topic :: System :: Networking
Classifier: Topic :: System :: Systems Administration
Classifier: Topic :: Utilities
Requires-Python: >=3.6
License-File: LICENSE.txt
Requires-Dist: aliyun-python-sdk-core>=2.13.15
Requires-Dist: aliyun-python-sdk-alidns>=2.0.18
Requires-Dist: setuptools>=39.0.1
Requires-Dist: acme>=1.0.0
Requires-Dist: certbot>=1.0.0
Provides-Extra: docs
Requires-Dist: Sphinx>=1.0; extra == "docs"
Requires-Dist: sphinx_rtd_theme; extra == "docs"
Dynamic: author
Dynamic: author-email
Dynamic: classifier
Dynamic: home-page
Dynamic: license
Dynamic: license-file
Dynamic: provides-extra
Dynamic: requires-dist
Dynamic: requires-python
Dynamic: summary
